bassmodelgens/__init__.py
bassmodelgens/bassmodelgens.py
bassmodelgens-0.1.1.dist-info/METADATA
bassmodelgens-0.1.1.dist-info/WHEEL
bassmodelgens-0.1.1.dist-info/licenses/LICENSE
bassmodelgens-0.1.1.dist-info/RECORD
